Workbook

Sheet Dissection Map
A1: Section | B1: Investigation Area | C1: Purpose / Item | D1: Sheet / Layer | E1: Cell / Range / Control | F1: Formula / Logic / Finding | G1: Status / Notes
A2: 1 | B2: Cylinder Definition / User Inputs | C2: True user-entry point | D2: OrderEntry UserForm | E2: Form | F2: The form title is "JIT 2026 Pricing Calculator". User selections are written into workbook cells and those cells drive the downstream formulas. | G2: VERIFIED from recovered OrderEntry VBA and form definition.
A3: 1 | B3: Cylinder Definition / User Inputs | C3: Customer | D3: OrderEntry -> Customer | E3: ComboBox2 -> Customer!B1 | F3: ComboBox2_Change writes the selected customer to Customer!B1. RowSource is Customer!B3:G10000. | G3: VERIFIED
A4: 1 | B4: Cylinder Definition / User Inputs | C4: Series | D4: OrderEntry -> Data | E4: ComboBox6 -> Data!B3 | F4: Series control. RowSource ShipVia!H2:H12. | G4: VERIFIED
A5: 1 | B5: Cylinder Definition / User Inputs | C5: Mount | D5: OrderEntry -> Data | E5: ComboBox5 -> Data!B5 | F5: Mount control. RowSource ShipVia!F2:F27. | G5: VERIFIED
A6: 1 | B6: Cylinder Definition / User Inputs | C6: Bore | D6: OrderEntry -> Data | E6: ComboBox11 -> Data!B4 | F6: Bore control. RowSource ShipVia!D21:D36. | G6: VERIFIED
A7: 1 | B7: Cylinder Definition / User Inputs | C7: Stroke | D7: OrderEntry -> Data | E7: TextBox22 -> likely Data!B8 | F7: Form label at the TextBox22 position is Stroke. Data!B8 is the workbook stroke input used by model and pricing formulas. | G7: STRONGLY INFERRED; direct ControlSource still to verify.
A8: 1 | B8: Cylinder Definition / User Inputs | C8: Rod | D8: OrderEntry -> Data | E8: ComboBox7 -> Data!B6 | F8: Rod control. RowSource ShipVia!K1:K6. | G8: VERIFIED
A9: 1 | B9: Cylinder Definition / User Inputs | C9: Rod Style / Thread | D9: OrderEntry -> Data | E9: ComboBox10 -> Data!D15 | F9: Form label is Style. RowSource ShipVia!D12:D16. D15 is used by model-code and rod-thread logic. | G9: VERIFIED
A10: 1 | B10: Cylinder Definition / User Inputs | C10: Cushion | D10: OrderEntry -> Data | E10: ComboBox12 -> Data!B7 | F10: Cushion control. RowSource ShipVia!E18:E24. | G10: VERIFIED
A11: 1 | B11: Cylinder Definition / User Inputs | C11: Ports | D11: OrderEntry -> Data | E11: ComboBox13 -> Data!D2 | F11: Ports control. RowSource ShipVia!E26:E29. | G11: VERIFIED
A12: 1 | B12: Cylinder Definition / User Inputs | C12: Seal | D12: OrderEntry -> Data | E12: ComboBox9 -> Data!B10 | F12: Seal control. RowSource ShipVia!D6:D11. | G12: VERIFIED
... A19: 1 | B19: Cylinder Definition / User Inputs | C19: Net Each display | D19: OrderEntry <- Data | E19: ListBox1 <- Data!D6 | F19: The form reads Data!D6 into ListBox1, labeled Net Each. This directly links the form to the central calculated cost/net value. | G19: VERIFIED
A20: 2 | B20: Model-Code Generation | C20: Model code assembly | D20: Data | E20: A1 | F20: =CONCATENATE(B3,B1,E5,B1,B4,C1,B8,C1,B6,B1,D15,B1,B7,B1,D2,B1,B10,B1,"S") | G20: VERIFIED; full Section 2 trace pending.
A21: 2 | B21: Model-Code Generation | C21: Mount/DRE model segment | D21: Data | E21: E5 | F21: =IF(D18="",B5,CONCATENATE("DRE/",B5)) | G21: VERIFIED
A22: 4 | B22: Base-Cylinder Component Cost | C22: Base component cost convergence | D22: Data | E22: C5 | F22: =H!Q52+A!Q53+MH!O52+PH!J34+IH!Q36+IMH!O27 | G22: VERIFIED
A23: 5 | B23: Stroke-Related Cost | C23: Stroke-related cost convergence | D23: Data | E23: C8 | F23: =H!W52+A!W53+MH!S52+PH!N34+IH!W36+IMH!S27 | G23: VERIFIED
A24: 6 | B24: Accessories and Adders | C24: Accessory total | D24: Data | E24: H23 | F24: =SUM(H8:H22)+H25 | G24: VERIFIED
A25: 6 | B25: Accessories and Adders | C25: Additional option total | D25: Data | E25: H33 | F25: =SUM(H26:H32) | G25: VERIFIED
A26: 8 | B26: Cost to List Price to Selling Price | C26: Central pricing convergence | D26: Data | E26: D6 | F26: Combines C5+C8+C10+H23+H33+series option sheet totals; applies (1-D4); if D18 nonblank adds C5*0.65; then adds H24 and ROUNDUP(...,0). | G26: VERIFIED
A27: 8 | B27: Cost to List Price to Selling Price | C27: List price | D27: Data | E27: I13 | F27: =D6/(1-D4) | G27: VERIFIED
A28: 9 | B28: Quote Presentation Logic | C28: Displayed list price | D28: Quote Form | E28: D11 | F28: =IF(Data!B3="W",Data!I13*0.85,Data!I13) | G28: VERIFIED
A29: 9 | B29: Quote Presentation Logic | C29: Standard sell price | D29: Quote Form | E29: F11 | F29: =D11*(1-E11) | G29: VERIFIED
A30: 9 | B30: Quote Presentation Logic | C30: Expedited price | D30: Quote Form | E30: F12 | F30: =IF(F11="","",IF(F11>1000,F11*1.3,F11*1.4)) | G30: VERIFIED
A31: 9 | B31: Quote Presentation Logic | C31: Emergency price | D31: Quote Form | E31: F13 | F31: =F12*1.25 | G31: VERIFIED
A32: 10 | B32: VBA Workflow | C32: Quote button workflow | D32: OrderEntry VBA | E32: CommandButton2_Click | F32: On Quote, VBA copies/sorts option selections, transfers selected option lines to Quote Form, restores quote formulas, updates ShipVia helper data, then returns to Quote Form. | G32: VERIFIED; detailed workflow deferred to Section 10.
A33: 3 | B33: Series Routing | C33: Section placeholder | G33: PENDING
A34: 7 | B34: Special-Order Pricing Rules | C34: Section placeholder | G34: PENDING
A35: 2 | B35: Model-Code Generation | C35: Authoritative model output | D35: Data | E35: A1 | F35: =CONCATENATE(B3,B1,E5,B1,B4,C1,B8,C1,B6,B1,D15,B1,B7,B1,D2,B1,B10,B1,"S") | G35: VERIFIED - central model-code constructor
A36: 2 | B36: Model-Code Generation | C36: Series segment | D36: OrderEntry -> Data | E36: Series -> Data!B3 | F36: Data!B3 is first segment of Data!A1. | G36: VERIFIED
A37: 2 | B37: Model-Code Generation | C37: Mount segment | D37: OrderEntry -> Data | E37: Mount -> Data!B5 -> Data!E5 | F37: E5 uses B5 normally; when D18 is populated it becomes "DRE/" & B5. | G37: VERIFIED
A38: 2 | B38: Model-Code Generation | C38: Bore segment | D38: OrderEntry -> Data | E38: Bore -> Data!B4 | F38: Inserted directly into A1. | G38: VERIFIED
A39: 2 | B39: Model-Code Generation | C39: Stroke segment | D39: OrderEntry -> Data | E39: Stroke -> Data!B8 | F39: Inserted directly into A1 between x separators. | G39: VERIFIED model dependency; Section 1 direct form control mapping still pending
A40: 2 | B40: Model-Code Generation | C40: Rod segment | D40: OrderEntry -> Data | E40: Rod -> Data!B6 | F40: Inserted directly into A1. | G40: VERIFIED
A41: 2 | B41: Model-Code Generation | C41: Rod-style segment | D41: OrderEntry -> Data | E41: Style -> Data!D15 | F41: Inserted directly into A1; D23 is description only. | G41: VERIFIED
A42: 2 | B42: Model-Code Generation | C42: Cushion segment | D42: OrderEntry -> Data | E42: Cushion -> Data!B7 | F42: Inserted directly into A1; D28 is description only. | G42: VERIFIED
A43: 2 | B43: Model-Code Generation | C43: Ports segment | D43: OrderEntry -> Data | E43: Ports -> Data!D2 | F43: Inserted directly into A1. | G43: VERIFIED
A44: 2 | B44: Model-Code Generation | C44: Seal segment | D44: OrderEntry -> Data | E44: Seal -> Data!B10 | F44: Inserted directly into A1; D30 is description only. | G44: VERIFIED
A45: 2 | B45: Model-Code Generation | C45: Model separators | D45: Data | E45: B1 / C1 | F45: B1="-"; C1="x". | G45: VERIFIED
A46: 2 | B46: Model-Code Generation | C46: Fixed suffix | D46: Data | E46: A1 literal | F46: Model always appends "-S" through B1 then literal "S". | G46: VERIFIED
A47: 2 | B47: Model-Code Generation | C47: Quote display | D47: Data -> Quote Form | E47: Quote Form!B12 = Data!A1 | F47: Quote form displays model string without another transformation. | G47: VERIFIED
... A63: 3 | B63: Series Routing | C63: Migration design rule | D63: Future HTML backend | E63: Series router | F63: Implement explicit primary calculator selection by series, then add shared option calculators. Avoid reproducing the workbook pattern of calculating every sheet. | G63: DESIGN IMPLICATION from verified routing.
A64: 4 | B64: Base-Cylinder Price Table / Base Amount | C64: Base-price convergence | D64: Data | E64: C5 | F64: =H!Q52+A!Q53+MH!O52+PH!J34+IH!Q36+IMH!O27 | G64: VERIFIED; primary base-price convergence. PH!J34 is blank in this workbook.
A65: 4 | B65: Base-Cylinder Price Table / Base Amount | C65: H-family total | D65: H | E65: Q52 | F65: =SUM(Q7:Q51) | G65: VERIFIED; H/HM/W base-price total.
A66: 4 | B66: Base-Cylinder Price Table / Base Amount | C66: H row match | D66: H | E66: Q7:Q51 | F66: Series H/HM/W + Bore M=row Data!B4 + Rod N=row Data!B6; returns SUM(R:V). | G66: VERIFIED
A67: 4 | B67: Base-Cylinder Price Table / Base Amount | C67: H mount bucket 1 | D67: H | E67: E7:E51 -> R7:R51 | F67: MX0/MX1/MX2/MX3 selected by Data!B5. | G67: VERIFIED
A68: 4 | B68: Base-Cylinder Price Table / Base Amount | C68: H mount bucket 2 | D68: H | E68: F7:F51 -> S7:S51 | F68: MF1/MF2/MS4 selected by Data!B5. | G68: VERIFIED
A69: 4 | B69: Base-Cylinder Price Table / Base Amount | C69: H mount bucket 3 | D69: H | E69: G7:G51 -> T7:T51 | F69: MP1/MP3/MT1/MT2/MF5/MF6/MS2/ME5/ME6. | G69: VERIFIED
A70: 4 | B70: Base-Cylinder Price Table / Base Amount | C70: H mount bucket 4 | D70: H | E70: H7:H51 -> U7:U51 | F70: MS3/ME3/ME4/MP2/MT4/MPU3/MS7. | G70: VERIFIED
A71: 4 | B71: Base-Cylinder Price Table / Base Amount | C71: A-family total | D71: A | E71: Q53 | F71: =SUM(Q6:Q52) | G71: VERIFIED; A/LH base-price total.
A72: 4 | B72: Base-Cylinder Price Table / Base Amount | C72: A row match | D72: A | E72: Q6:Q52 | F72: Series A/LH + Bore M=row Data!B4 + Rod N=row Data!B6; returns SUM(R:V). | G72: VERIFIED
A73: 4 | B73: Base-Cylinder Price Table / Base Amount | C73: A mount buckets | D73: A | E73: E:H -> R:U | F73: Four stored price buckets selected by Data!B5; mount membership differs slightly from H. | G73: VERIFIED
A74: 4 | B74: Base-Cylinder Price Table / Base Amount | C74: MH total | D74: MH | E74: O52 | F74: =SUM(O7:O51) | G74: VERIFIED; MH base-price total.
A75: 4 | B75: Base-Cylinder Price Table / Base Amount | C75: MH row match | D75: MH | E75: O7:O51 | F75: Series MH + Bore K=row Data!B4 + Rod L=row Data!B6; returns SUM(P:R). | G75: VERIFIED
A76: 4 | B76: Base-Cylinder Price Table / Base Amount | C76: MH mount bucket E | D76: MH | E76: E7:E51 -> P7:P51 | F76: MF1/MF2/MF5/MF6/MS3/MP1/MP3/MS2/ME5/ME6. | G76: VERIFIED
A77: 4 | B77: Base-Cylinder Price Table / Base Amount | C77: MH mount bucket F | D77: MH | E77: F7:F51 -> Q7:Q51 | F77: MT4/MPU3/MS7/MT1/MT2/ME3/ME4. | G77: VERIFIED
A78: 4 | B78: Base-Cylinder Price Table / Base Amount | C78: IH/IHM total | D78: IH | E78: Q36 | F78: =SUM(Q7:Q35) | G78: VERIFIED; metric IH/IHM base-price total.
A79: 4 | B79: Base-Cylinder Price Table / Base Amount | C79: IH row match and mount buckets | D79: IH | E79: Q7:Q35; E:H -> R:U | F79: Same four-bucket structure as H, using metric bore/rod values. | G79: VERIFIED
A80: 4 | B80: Base-Cylinder Price Table / Base Amount | C80: IMH total | D80: IMH | E80: O27 | F80: =SUM(O7:O26) | G80: VERIFIED; metric IMH base-price total.
A81: 4 | B81: Base-Cylinder Price Table / Base Amount | C81: IMH row match and mount buckets | D81: IMH | E81: O7:O26; E:F -> P:Q | F81: Same two-bucket structure as MH, using metric bore/rod values. | G81: VERIFIED
A82: 4 | B82: Base-Cylinder Price Table / Base Amount | C82: PH reference inside C5 | D82: PH | E82: J34 | F82: Blank cell; contributes zero to Data!C5 in this workbook. | G82: VERIFIED; position sensing is added elsewhere, notably PH!A33 in Data!D6.
A83: 4 | B83: Base-Cylinder Price Table / Base Amount | C83: Architecture conclusion | D83: Future HTML pricing engine | E83: Base price lookup | F83: Series + Bore + Rod + Mount Group -> Base Price | G83: VERIFIED design abstraction from workbook logic.
A84: 5 | B84: Stroke-Related Cost | C84: Central aggregator | D84: Data | E84: C8 | F84: =H!W52+A!W53+MH!S52+PH!N34+IH!W36+IMH!S27 | G84: VERIFIED; combined stroke + cushion amount, not stroke-only.
A85: 5 | B85: Stroke-Related Cost | C85: Stroke input | D85: OrderEntry -> Data | E85: Data!B8 | F85: Stroke input used by Data!A1 and every active-series stroke formula. | G85: VERIFIED as downstream input; direct form ControlSource remained previously inferred.
A86: 5 | B86: Stroke-Related Cost | C86: Cushion input | D86: OrderEntry -> Data | E86: Data!B7 | F86: Cushion code; ShipVia!E18:E24 lists NC, RE, CE, BE, ARE, ACE, ABE. | G86: VERIFIED
A87: 5 | B87: Stroke-Related Cost | C87: H/HM/W total | D87: H | E87: W52 | F87: =SUM(W7:W51) | G87: VERIFIED
A88: 5 | B88: Stroke-Related Cost | C88: H row formula | D88: H | E88: W7:W51 | F88: If Q row is active: cushion multiplier*K row + J row*ROUNDUP(Data!B8,0.1). | G88: VERIFIED
A89: 5 | B89: Stroke-Related Cost | C89: H stroke rates | D89: H | E89: J7:J51 | F89: Single Rod Add Per inch of Stroke; row-specific hardcoded values. | G89: VERIFIED
A90: 5 | B90: Stroke-Related Cost | C90: H cushion rates | D90: H | E90: K7:K51 | F90: Add For Cushion Per End; row-specific hardcoded values. | G90: VERIFIED
A91: 5 | B91: Stroke-Related Cost | C91: A/LH total | D91: A | E91: W53 | F91: =SUM(W6:W52) | G91: VERIFIED
A92: 5 | B92: Stroke-Related Cost | C92: A row formula | D92: A | E92: W6:W52 | F92: Same structure as H: cushion multiplier*K + J*ROUNDUP(Data!B8,0.1). | G92: VERIFIED
A93: 5 | B93: Stroke-Related Cost | C93: MH total | D93: MH | E93: S52 | F93: =SUM(S7:S51) | G93: VERIFIED
A94: 5 | B94: Stroke-Related Cost | C94: MH row formula | D94: MH | E94: S7:S51 | F94: If O row active: BE=2*I; CE/RE=1*I; otherwise 0 cushion + H*ROUNDUP(Data!B8,0.1). | G94: VERIFIED
A95: 5 | B95: Stroke-Related Cost | C95: IH/IHM total | D95: IH | E95: W36 | F95: =SUM(W7:W35) | G95: VERIFIED; metric per-mm stroke rates.
A96: 5 | B96: Stroke-Related Cost | C96: IH row formula | D96: IH | E96: W7:W35 | F96: Same cushion multiplier structure as H/A; J is per mm, K cushion-per-end. | G96: VERIFIED
A97: 5 | B97: Stroke-Related Cost | C97: IMH total | D97: IMH | E97: S27 | F97: =SUM(S7:S26) | G97: VERIFIED; metric per-mm stroke rates.
A98: 5 | B98: Stroke-Related Cost | C98: IMH row formula | D98: IMH | E98: S7:S26 | F98: Same structure as MH; H is per mm, I cushion-per-end. | G98: VERIFIED
A99: 5 | B99: Stroke-Related Cost | C99: PH reference | D99: PH | E99: N34 | F99: Blank in this workbook; contributes zero to Data!C8. | G99: VERIFIED
A100: 5 | B100: Stroke-Related Cost | C100: Cushion multiplier | D100: H/A/IH | E100: W-row formula | F100: NC/other=0; RE=1; CE=1; BE=2; ARE=2; ACE=2; ABE=4. | G100: VERIFIED
A101: 5 | B101: Stroke-Related Cost | C101: Cushion multiplier | D101: MH/IMH | E101: S-row formula | F101: NC/other=0; RE=1; CE=1; BE=2; ARE/ACE/ABE are not handled and therefore produce 0 cushion add. | G101: VERIFIED
A102: 5 | B102: Stroke-Related Cost | C102: Architecture conclusion | D102: Future HTML pricing engine | E102: Stroke + cushion rule | F102: Selected price-table row supplies StrokeRate and CushionRate; compute stroke add plus code-based cushion multiplier. | G102: VERIFIED design abstraction.
A103: 5 | B103: Stroke-Related Cost | C103: Implementation caution | D103: Future HTML pricing engine | E103: ROUNDUP(Data!B8,0.1) | F103: Reproduce Excel behavior with test cases before simplifying the rounding expression. | G103: OPEN IMPLEMENTATION TEST; source formula VERIFIED.
A104: 6 | B104: Accessories and Adders | C104: Direct accessory total | D104: Data | E104: H23 | F104: =SUM(H8:H22)+H25 | G104: VERIFIED; direct accessory block added to Data!D6.
A105: 6 | B105: Accessories and Adders | C105: Rod Clevis through Jam Nut quantities | D105: Data | E105: G9:G22 | F105: User-entered quantities drive H9:H22 using Acc price cells. | G105: VERIFIED
A106: 6 | B106: Accessories and Adders | C106: Standard Rod Boot | D106: Data / Acc | E106: Data!H25 / Acc!D69 | F106: Acc!D69 sums rod-diameter-specific base + stroke price when Data!G25 > 0.01. | G106: VERIFIED
A107: 6 | B107: Accessories and Adders | C107: Special option total | D107: Data | E107: H33 | F107: =SUM(H26:H32) | G107: VERIFIED; free-form special option block.
A108: 6 | B108: Accessories and Adders | C108: Special option descriptions | D108: Data / ShipVia | E108: F26:F31 -> ShipVia!A24:A29 | F108: Descriptions are mirrored to ShipVia for lookup. | G108: VERIFIED
A109: 6 | B109: Accessories and Adders | C109: Special option lookup | D109: ShipVia | E109: B24:C29 | F109: VLOOKUP descriptions against ShipVia!A52:C484; column C is used by Data!H26:H31. | G109: VERIFIED
A110: 6 | B110: Accessories and Adders | C110: H-family common mods 1 | D110: H2 | E110: R53 | F110: =SUM(M53:Q53) | G110: VERIFIED; rod extension, stop tube, stainless rod, chrome bore, thread extension.
A111: 6 | B111: Accessories and Adders | C111: H-family common mods 2 | D111: H3 | E111: T53 | F111: =SUM(N53:S53)+T54 | G111: VERIFIED; gland drain, air bleed, prox, brass wiper, Viton, extra ports, light-duty mill.
A112: 6 | B112: Accessories and Adders | C112: H-family common mods 3 | D112: H4 | E112: R53 | F112: =SUM(M53:Q53)+R54 | G112: VERIFIED; flange port, extra tie rod, CIPR, UltraOx, special seals.
A113: 6 | B113: Accessories and Adders | C113: A/LH common mods 1 | D113: A2 | E113: O55 | F113: =SUM(K55:N55) | G113: VERIFIED; rod extension, stop tube, stainless rod, thread extension.
A114: 6 | B114: Accessories and Adders | C114: A/LH common mods 2 | D114: A3 | E114: Q55 | F114: =SUM(L55:P55) | G114: VERIFIED; air bleed, prox, brass wiper, seals, extra ports.
A115: 6 | B115: Accessories and Adders | C115: A/LH common mods 3 reference | D115: A4 | E115: O55 | F115: Blank in current workbook but referenced in Data!D6. | G115: VERIFIED blank / legacy-reserved reference.
A116: 6 | B116: Accessories and Adders | C116: Metric common mods 1 | D116: IH2 | E116: R37 | F116: =SUM(M37:Q37) | G116: VERIFIED; metric rod extension, stop tube, stainless rod, chrome bore, thread extension.
A117: 6 | B117: Accessories and Adders | C117: Metric common mods 2 | D117: IH3 | E117: U37 | F117: =SUM(N37:T37) | G117: VERIFIED; gland drain, air bleed, prox, brass wiper, special seals, extra ports.
A118: 6 | B118: Accessories and Adders | C118: Metric common mods 3 | D118: IH4 | E118: S37 | F118: =SUM(M37:R37) | G118: VERIFIED; flange port, extra tie rod, CIPR, UltraOx, special seals.
A119: 6 | B119: Accessories and Adders | C119: Position-sensing total | D119: PH | E119: A33 | F119: =IF(L33>1,L33,D32+H20+I20+J20) | G119: VERIFIED; chooses metric branch when L33 > 1, otherwise imperial branch.
A120: 6 | B120: Accessories and Adders | C120: PH gun drilling / transducer | D120: PH | E120: H5:H20 / S5:S20 | F120: Triggered by Data!B18 or B22; base + stroke rate keyed by bore. | G120: VERIFIED
A121: 6 | B121: Accessories and Adders | C121: PH sensor cover | D121: PH | E121: I5:I20 / T5:T20 | F121: Triggered by Data!B24; certain MP mounts double price. | G121: VERIFIED
...
